geliver/__init__.py
geliver/client.py
geliver/models.py
geliver/requests.py
geliver/types.py
geliver/webhooks.py
geliver-0.3.1.dist-info/licenses/LICENSE
geliver-0.3.1.dist-info/METADATA
geliver-0.3.1.dist-info/WHEEL
geliver-0.3.1.dist-info/top_level.txt
geliver-0.3.1.dist-info/RECORD
