Metadata-Version: 2.4
Name: geliver
Version: 0.3.1
Summary: Geliver API SDK (Python)
License: This LICENSE file applies to the Geliver SDK source code and documentation in
Requires-Python: >=3.9
License-File: LICENSE
Requires-Dist: httpx>=0.27
Requires-Dist: pydantic>=2.6
Dynamic: license-file
